rud/__init__.py
rud/__main__.py
rud/cli.py
rud/config.py
rud/downloaded.py
rud/downloader.py
rud-0.0.4.dist-info/LICENSE
rud-0.0.4.dist-info/METADATA
rud-0.0.4.dist-info/WHEEL
rud-0.0.4.dist-info/entry_points.txt
rud-0.0.4.dist-info/top_level.txt
rud-0.0.4.dist-info/RECORD
